[1,["1fpIcjgfZOdp/c/FHocMm7"],["_textureSetter"],["cc.SpriteFrame"],0,[[[{"name":"rou","rect":[1014,389,50,43],"offset":[0,0],"originalSize":[50,43],"capInsets":[0,0,0,0]}],[0],0,[0],[0],[0]],[[{"name":"战斗界面底部jindu01","rect":[753,97,258,107],"offset":[0,0],"originalSize":[258,107],"capInsets":[0,0,0,0]}],[0],0,[0],[0],[0]],[[{"name":"战斗界面底部jindu02","rect":[753,206,258,107],"offset":[0,0],"originalSize":[258,107],"capInsets":[0,0,0,0]}],[0],0,[0],[0],[0]],[[{"name":"战斗界面底部","rect":[1,1,750,149],"offset":[0,0],"originalSize":[750,149],"capInsets":[0,0,0,0]}],[0],0,[0],[0],[0]]]]